Metadata-Version: 2.1
Name: MultiPython
Version: 0.1
Summary: MultiPy library for Python.
Home-page: https://github.com/mad-cs/multipy
Author-email: 
License: PSL
Keywords: file
Platform: UNKNOWN
